intelex.py
intelex-0.0.30.dist-info/LICENSE.txt
intelex-0.0.30.dist-info/METADATA
intelex-0.0.30.dist-info/WHEEL
intelex-0.0.30.dist-info/top_level.txt
intelex-0.0.30.dist-info/RECORD
