Metadata-Version: 2.1
Name: intelex
Version: 0.0.30
Summary: Intelex SDK
Home-page: https://github.com/thomassampson/intelex_sdk
Author: Thomas Sampson
Author-email: sampsont91@gmail.com
License: UNKNOWN
Platform: UNKNOWN
Classifier: Development Status :: 3 - Alpha
Classifier: License :: OSI Approved :: GNU General Public License v3 (GPLv3)
Classifier: Operating System :: OS Independent
Classifier: Programming Language :: Python :: 3
Classifier: Programming Language :: Python :: 3.6
Classifier: Programming Language :: Python :: 3.7
